slackmentions.py
slackmentions-0.1.2.dist-info/DESCRIPTION.rst
slackmentions-0.1.2.dist-info/METADATA
slackmentions-0.1.2.dist-info/RECORD
slackmentions-0.1.2.dist-info/WHEEL
slackmentions-0.1.2.dist-info/metadata.json
slackmentions-0.1.2.dist-info/top_level.txt
