Metadata-Version: 2.0
Name: slackmentions
Version: 0.1.2
Summary: Some functions for dealing with mentions in slack messages
Home-page: https://github.com/rickh94/slackmentions
Author: Rick Henry
Author-email: fredericmhenry@gmail.com
License: MIT
Keywords: slack,text,messages,mentions
Platform: UNKNOWN
Classifier: License :: OSI Approved :: MIT License
Classifier: Programming Language :: Python :: 3
Classifier: Programming Language :: Python :: 3.4
Classifier: Programming Language :: Python :: 3.5
Classifier: Programming Language :: Python :: 3.6
Classifier: Operating System :: OS Independent
Classifier: Topic :: Communications :: Chat
Requires-Python: >=3
Requires-Dist: slackperson
